nap_plot_tools/__init__.py
nap_plot_tools/cmap.py
nap_plot_tools/tools.py
nap_plot_tools/_tests/__init__.py
nap_plot_tools/_tests/test_tools.py
nap_plot_tools-0.1.2.dist-info/LICENSE
nap_plot_tools-0.1.2.dist-info/METADATA
nap_plot_tools-0.1.2.dist-info/WHEEL
nap_plot_tools-0.1.2.dist-info/top_level.txt
nap_plot_tools-0.1.2.dist-info/RECORD
