Metadata-Version: 2.1
Name: nap-plot-tools
Version: 0.1.2
Summary: A NAPari PLOTter TOOLbar and tools for additional functionalities.
Home-page: https://github.com/zoccoler/nap-plot-tools
Author: Marcelo Leomil Zoccoler
Author-email: marzoccoler@gmail.com
License: BSD-3-Clause
Project-URL: Bug Tracker, https://github.com/zoccoler/nap-plot-tools/issues
Project-URL: Documentation, https://github.com/zoccoler/nap-plot-tools#README.md
Project-URL: Source Code, https://github.com/zoccoler/nap-plot-tools
Project-URL: User Support, https://github.com/zoccoler/nap-plot-tools/issues
Classifier: Development Status :: 2 - Pre-Alpha
Classifier: Framework :: napari
Classifier: Intended Audience :: Developers
Classifier: License :: OSI Approved :: BSD License
Classifier: Operating System :: OS Independent
Classifier: Programming Language :: Python
Classifier: Programming Language :: Python :: 3
Classifier: Programming Language :: Python :: 3 :: Only
Classifier: Programming Language :: Python :: 3.8
Classifier: Programming Language :: Python :: 3.9
Classifier: Programming Language :: Python :: 3.10
Classifier: Topic :: Scientific/Engineering :: Image Processing
Requires-Python: >=3.8
License-File: LICENSE
Requires-Dist: numpy
Requires-Dist: qtpy
Requires-Dist: cmap
Requires-Dist: deprecated
Requires-Dist: matplotlib
Provides-Extra: testing
Requires-Dist: tox; extra == "testing"
Requires-Dist: pytest; extra == "testing"
Requires-Dist: pytest-cov; extra == "testing"
Requires-Dist: pytest-qt; extra == "testing"
Requires-Dist: pyqt5; extra == "testing"
Requires-Dist: deprecated; extra == "testing"
Requires-Dist: napari; extra == "testing"
Requires-Dist: napari-matplotlib; extra == "testing"
